[
  {
    "pdv": "san-martín",
    "pdvF": "San Martín"
  },
  {
    "pdv": "plaza-bocagrande",
    "pdvF": "Plaza Bocagrande"
  },
  {
    "pdv": "san-juan",
    "pdvF": "San Juan"
  },
  {
    "pdv": "san-pedro",
    "pdvF": "San Pedro"
  },
  {
    "pdv": "san-diego",
    "pdvF": "San Diego"
  },
  {
    "pdv": "serrezuela",
    "pdvF": "Serrezuela"
  },
  {
    "pdv": "mall-plaza",
    "pdvF": "Mall Plaza"
  },
  {
    "pdv": "caribe-plaza",
    "pdvF": "Caribe plaza"
  },
  {
    "pdv": "oficinas-administrativas",
    "pdvF": "Oficinas administrivas"
  },
  {
    "pdv": "zazue",
    "pdvF": "Zazue"
   },
   {
    "pdv": "casacentro",
    "pdvF": "Casacentro"
  },
  {
    "pdv": "buena-vista",
    "pdvF": "Buena vista"
  }
]